{"data": {"BTC": {"price": 64214.27, "change": 1.63}, "ETH": {"price": 1783.31, "change": 2.24}, "XAU": {"price": 4106.0, "change": -0.84}, "IHSG": {"price": 5906.73, "change": -0.1}, "USDIDR": {"price": 18050.0, "change": -0.19}, "TLKM": {"price": 2460.0, "change": -1.99}, "BBRI": {"price": 2770.0, "change": -0.36}, "BBCA": {"price": 6150.0, "change": -0.81}, "ASII": {"price": 4790.0, "change": -1.84}, "UNVR": {"price": 1720.0, "change": 0.29}, "BMRI": {"price": 4050.0, "change": 0.25}, "SPX": {"price": 7543.64, "change": 0.81}}}